mdformat_simple_breaks/__init__.py
mdformat_simple_breaks/plugin.py
mdformat_simple_breaks-0.0.1.dist-info/entry_points.txt
mdformat_simple_breaks-0.0.1.dist-info/LICENSE
mdformat_simple_breaks-0.0.1.dist-info/WHEEL
mdformat_simple_breaks-0.0.1.dist-info/METADATA
mdformat_simple_breaks-0.0.1.dist-info/RECORD
